tungstenkit/__init__.py
tungstenkit/_internal/__init__.py
tungstenkit/_internal/blob_store.py
tungstenkit/_internal/cli/__init__.py
tungstenkit/_internal/cli/callbacks.py
tungstenkit/_internal/cli/login_command.py
tungstenkit/_internal/cli/main.py
tungstenkit/_internal/cli/model_commands.py
tungstenkit/_internal/cli/options.py
tungstenkit/_internal/cli/project_commands.py
tungstenkit/_internal/configs.py
tungstenkit/_internal/constants.py
tungstenkit/_internal/containerize/__init__.py
tungstenkit/_internal/containerize/build_context.py
tungstenkit/_internal/containerize/containerize_model.py
tungstenkit/_internal/containerize/dockerfile_generators/__init__.py
tungstenkit/_internal/containerize/dockerfile_generators/base_dockerfile_generator.py
tungstenkit/_internal/containerize/dockerfile_generators/base_images/__init__.py
tungstenkit/_internal/containerize/dockerfile_generators/base_images/base_image.py
tungstenkit/_internal/containerize/dockerfile_generators/base_images/common.py
tungstenkit/_internal/containerize/dockerfile_generators/base_images/conda_image.py
tungstenkit/_internal/containerize/dockerfile_generators/base_images/cuda_image.py
tungstenkit/_internal/containerize/dockerfile_generators/base_images/custom_image.py
tungstenkit/_internal/containerize/dockerfile_generators/base_images/python_image.py
tungstenkit/_internal/containerize/dockerfile_generators/dockerfile_generator_factory.py
tungstenkit/_internal/containerize/dockerfile_generators/gpu_pkg_collections/__init__.py
tungstenkit/_internal/containerize/dockerfile_generators/gpu_pkg_collections/base_collection.py
tungstenkit/_internal/containerize/dockerfile_generators/gpu_pkg_collections/common.py
tungstenkit/_internal/containerize/dockerfile_generators/gpu_pkg_collections/tf_collection.py
tungstenkit/_internal/containerize/dockerfile_generators/gpu_pkg_collections/torch_collection.py
tungstenkit/_internal/containerize/dockerfile_generators/metadata/__init__.py
tungstenkit-0.2.20.dist-info/LICENSE
tungstenkit-0.2.20.dist-info/METADATA
tungstenkit-0.2.20.dist-info/WHEEL
tungstenkit-0.2.20.dist-info/entry_points.txt
tungstenkit-0.2.20.dist-info/RECORD
