Metadata-Version: 2.1
Name: tungstenkit
Version: 0.2.20
Summary: ML container made simple
Home-page: https://github.com/tungsten-ai/tungstenkit
Author: Tungsten Contributors
Author-email: foss@tungsten-ai.com
Requires-Python: >=3.7,<4.0
Classifier: Development Status :: 3 - Alpha
Classifier: Environment :: Console
Classifier: Environment :: GPU
Classifier: Environment :: Web Environment
Classifier: Framework :: FastAPI
Classifier: Framework :: Pydantic
Classifier: Framework :: Pydantic :: 1
Classifier: Intended Audience :: Developers
Classifier: Intended Audience :: Information Technology
Classifier: Intended Audience :: Science/Research
Classifier: License :: OSI Approved :: Apache Software License
Classifier: Operating System :: OS Independent
Classifier: Programming Language :: Python
Classifier: Programming Language :: Python :: 3
Classifier: Programming Language :: Python :: 3.7
Classifier: Programming Language :: Python :: 3.8
Classifier: Programming Language :: Python :: 3.9
Classifier: Programming Language :: Python :: 3.10
Classifier: Programming Language :: Python :: 3.11
Classifier: Programming Language :: Python :: 3 :: Only
Classifier: Topic :: Scientific/Engineering
Classifier: Topic :: Scientific/Engineering :: Artificial Intelligence
Classifier: Topic :: Software Development
Classifier: Topic :: Software Development :: Build Tools
Classifier: Topic :: Software Development :: Libraries
Classifier: Topic :: Software Development :: Libraries :: Python Modules
Classifier: Topic :: Software Development :: User Interfaces
Classifier: Typing :: Typed
Requires-Dist: attrs (>=22)
Requires-Dist: beautifulsoup4 (>=4.11.1,<5.0.0)
Requires-Dist: binaryornot (>=0.4.4,<0.5.0)
Requires-Dist: cattrs (>=22)
Requires-Dist: dill (>=0.3.6,<0.4.0)
Requires-Dist: docker (>=6.0.1,<7.0.0)
Requires-Dist: fastapi (>=0.88.0,<1.0.0)
Requires-Dist: fasteners (>=0.18,<0.19)
Requires-Dist: filelock (>=3.9.0,<4.0.0)
Requires-Dist: furl (>=2.1.3,<3.0.0)
Requires-Dist: jinja2 (>=3.1.2,<4.0.0)
Requires-Dist: jsonref (>=1.1.0,<2.0.0)
Requires-Dist: loguru (>=0.6.0,<1.0.0)
Requires-Dist: markdown (>=3.4.1,<4.0.0)
Requires-Dist: markdownify (>=0.11.6,<0.12.0)
Requires-Dist: pathspec (>=0.10.2,<0.11.0)
Requires-Dist: pillow (>=5.2.0)
Requires-Dist: platformdirs (>=3.8.1,<4.0.0)
Requires-Dist: pydantic (>=1.10.2,<2.0.0)
Requires-Dist: pynvml (>=11.5.0,<12.0.0)
Requires-Dist: python-multipart (>=0.0.6,<0.0.7)
Requires-Dist: pytz (>=2023.3.post1,<2024.0)
Requires-Dist: pyyaml (>=5.3.1)
Requires-Dist: requests (>=2.25.1,<=2.31.0)
Requires-Dist: requests-toolbelt (>=0.10.1,<0.11.0)
Requires-Dist: rich (>=13.3.1,<14.0.0)
Requires-Dist: tabulate (>=0.9.0,<0.10.0)
Requires-Dist: typing-extensions (>=4.4.0,<5.0.0)
Requires-Dist: urllib3 (>=1.26,<2.0)
Requires-Dist: uvicorn (>=0.17.6,<1.0.0)
Requires-Dist: w3lib (>=2.1.1,<3.0.0)
